{
	"1_2_Sideflip WK": ["17.63", "Raisn"],
	"2_5_Cannon (Pole)": ["12.46", "Abood"],
	"3_6_Beginner": ["11", "Raisn"],
	"5_1_Elevator Clip": ["19.53", "Multiple"],
	"5_4_No Clip": ["37.7", "Raisn"],
	"6_1_Ledgegrab": ["19.56", "Raisn"],
	"6_5_TJ Boost": ["22.23", "toastrider"],
	"6_5_Beginner": ["27.6", "LFoxy"],
	"7_3_Shell": ["29.3", "Abood"],
	"7_5_Backside": ["53.56", "Zinsch"],
	"7_5_TJWK": ["52.23", "Sanj"],
	"9_1_Beginner": ["10.90", "Machochin"],
	"11_1_No Log WK": ["19.5", "Raisn"],
	"11_2_No Log WK": ["43.13", "Twig"],
	"11_5_Slidekick (No LWK)": ["18.9", "Raisn"],
	"11_5_No Log WK": ["17.9", "Nobody"],
	"11_6_Beginner": ["11.06", "Multiple"],
	"12_3_Intended": ["47.86", "tjk"],
	"12_4_Beginner": ["23.36", "Raisn"],
	"14_1_No Bounce": ["38.7", "Raisn"],
	"14_4_Flame TJ": ["16.9", "emma"],
	"14_5_Beginner": ["14.36", "Raisn"],
	"14_6_No Bounce": ["38.7", "Raisn"],
	"16_3n_Pole": ["47.13", "FGSM"]
}